cli/__init__.py
cli/apps/AppInterface.py
cli/apps/__init__.py
cli/apps/aggregate/__init__.py
cli/apps/observables/__init__.py
lstpressure/__init__.py
lstpressure/conf/__init__.py
lstpressure/logger/__init__.py
lstpressure/lst/LST.py
lstpressure/lst/__init__.py
lstpressure/lst/helpers/__init__.py
lstpressure/lst/helpers/calculate_observables.py
lstpressure/lst/helpers/calculate_observations.py
lstpressure/lstcalendar/LSTCalendar.py
lstpressure/lstcalendar/LSTCalendarDate.py
lstpressure/lstcalendar/__init__.py
lstpressure/lstindex/LSTIndex.py
lstpressure/lstindex/LSTInterval.py
lstpressure/lstindex/LSTIntervalType.py
lstpressure/lstindex/__init__.py
lstpressure/observable/Observable.py
lstpressure/observable/__init__.py
lstpressure/observation/Observation.py
lstpressure/observation/__init__.py
lstpressure/observation/is_observable.py
lstpressure/perf/__init__.py
lstpressure/sun/Sun.py
lstpressure/sun/__init__.py
lstpressure/sun/location_providers/LocationProvider.py
lstpressure/sun/location_providers/__init__.py
lstpressure/sun/location_providers/normalize_intervals.py
lstpressure/sun/location_providers/astral_provider/AstralProvider.py
lstpressure/sun/location_providers/astral_provider/__init__.py
lstpressure/sun/location_providers/meerkat_provider/AstroUtils.py
lstpressure/sun/location_providers/meerkat_provider/DateTimeUtils.py
lstpressure/sun/location_providers/meerkat_provider/MeerKATProvider.py
lstpressure/sun/location_providers/meerkat_provider/SolarSystemUtils.py
lstpressure/sun/location_providers/meerkat_provider/__init__.py
lstpressure/sun/location_providers/meerkat_provider/planets.json
lstpressure/utils/__init__.py
lstpressure/utils/normalize_coordinates.py
lstpressure/utils/normalize_date.py
lstpressure/utils/time_conversions.py
tests/__init__.py
tests/conftest.py
tests/test_lib_astral.py
tests/test_lib_meerkat.py
tests/lstcalendar/__init__.py
tests/lstcalendar/test_LSTCalendar.py
tests/lstcalendar/test_LSTCalendarDate.py
lst_pressure-1.8.6.dist-info/LICENSE
lst_pressure-1.8.6.dist-info/METADATA
lst_pressure-1.8.6.dist-info/WHEEL
lst_pressure-1.8.6.dist-info/top_level.txt
lst_pressure-1.8.6.dist-info/RECORD
