Metadata-Version: 2.1
Name: lst-pressure
Version: 1.8.6
Summary: Determine periods of "LST pressure" by querying for intersections between LST/Solar intervals
Home-page: https://github.com/ska-sa/lst-pressure
Author: Zach Smith
Author-email: zsmith@sarao.ac.za
License: Apache 2.0
Classifier: License :: OSI Approved :: Apache Software License
Classifier: Programming Language :: Python :: 3
Classifier: Programming Language :: Python :: 3.12
Requires-Python: >=3.12
License-File: LICENSE
Requires-Dist: agate ==1.12.0
Requires-Dist: agate-dbf ==0.2.3
Requires-Dist: agate-excel ==0.4.1
Requires-Dist: agate-sql ==0.7.2
Requires-Dist: aiofiles ==24.1.0
Requires-Dist: astral ==3.2
Requires-Dist: astropy ==6.1.6
Requires-Dist: astropy-iers-data ==0.2024.11.18.0.35.2
Requires-Dist: babel ==2.16.0
Requires-Dist: build ==1.2.2.post1
Requires-Dist: cfgv ==3.4.0
Requires-Dist: csvkit ==2.0.1
Requires-Dist: dbfread ==2.0.7
Requires-Dist: distlib ==0.3.9
Requires-Dist: duckdb ==1.1.3
Requires-Dist: duckdb-engine ==0.13.5
Requires-Dist: et-xmlfile ==2.0.0
Requires-Dist: filelock ==3.16.1
Requires-Dist: greenlet ==3.1.1
Requires-Dist: identify ==2.6.2
Requires-Dist: intervaltree ==3.1.0
Requires-Dist: isodate ==0.7.2
Requires-Dist: katversion ==1.2
Requires-Dist: leather ==0.4.0
Requires-Dist: nodeenv ==1.9.1
Requires-Dist: numpy ==2.1.3
Requires-Dist: olefile ==0.47
Requires-Dist: openpyxl ==3.1.5
Requires-Dist: packaging ==24.2
Requires-Dist: pandas ==2.2.3
Requires-Dist: parsedatetime ==2.6
Requires-Dist: platformdirs ==4.3.6
Requires-Dist: pyarrow ==18.0.0
Requires-Dist: pyerfa ==2.0.1.5
Requires-Dist: pyproject-hooks ==1.2.0
Requires-Dist: python-dateutil ==2.9.0.post0
Requires-Dist: python-dotenv ==1.0.1
Requires-Dist: python-slugify ==8.0.4
Requires-Dist: pytimeparse ==1.1.8
Requires-Dist: pytz ==2024.2
Requires-Dist: PyYAML ==6.0.2
Requires-Dist: setuptools ==75.5.0
Requires-Dist: six ==1.16.0
Requires-Dist: sortedcontainers ==2.4.0
Requires-Dist: SQLAlchemy ==2.0.36
Requires-Dist: text-unidecode ==1.3
Requires-Dist: typing-extensions ==4.12.2
Requires-Dist: tzdata ==2024.2
Requires-Dist: virtualenv ==20.27.1
Requires-Dist: xlrd ==2.0.1
